datadev/__init__.py
datadev/shared/drinkme.txt
datadev/shared/tableaulogo.txt
datadev-1.0.12.dist-info/DESCRIPTION.rst
datadev-1.0.12.dist-info/METADATA
datadev-1.0.12.dist-info/RECORD
datadev-1.0.12.dist-info/WHEEL
datadev-1.0.12.dist-info/entry_points.txt
datadev-1.0.12.dist-info/metadata.json
datadev-1.0.12.dist-info/top_level.txt
