Metadata-Version: 2.0
Name: datadev
Version: 1.0.12
Summary: Make Datadev rad.
Home-page: https://github.com/tableau/datadev
Author: Tableau
Author-email: github@tableau.com
License: MIT
Platform: UNKNOWN
